ftd2xx_aio-0.1.0.dist-info/METADATA
ftd2xx_aio-0.1.0.dist-info/WHEEL
ftd2xx_aio-0.1.0.dist-info/licenses/LICENSE
ftd2xx_aio/__init__.py
ftd2xx_aio/aio.py
ftd2xx_aio/protocols.py
ftd2xx_aio/transports.py
ftd2xx_aio-0.1.0.dist-info/RECORD
