Metadata-Version: 2.1
Name: ftd2xx-aio
Version: 0.1.0
Summary: Transport/protocol layer to extend ftd2xx for asyncronous connections.
Keywords: ftd2xx asyncio serial usb
Home-page: https://github.com/ftd2xx/ftd2xx-aio
Author: Krister Wikstrom
License: MIT
Classifier: Programming Language :: Python :: 3
Classifier: Programming Language :: Python :: 3.9
Classifier: Programming Language :: Python :: 3.10
Classifier: Programming Language :: Python :: 3.11
Classifier: Programming Language :: Python :: 3.12
Project-URL: Homepage, https://github.com/ftd2xx/ftd2xx-aio
Requires-Python: >=3.9
Requires-Dist: ftd2xx>=1.3.3
